adactivexlsx2html/__init__.py
adactivexlsx2html/__main__.py
adactivexlsx2html/compat.py
adactivexlsx2html/core.py
adactivexlsx2html/constants/__init__.py
adactivexlsx2html/constants/border.py
adactivexlsx2html/constants/builtin.py
adactivexlsx2html/constants/locale_format.py
adactivexlsx2html/format/__init__.py
adactivexlsx2html/format/dt.py
adactivexlsx2html/format/hyperlink.py
adactivexlsx2html/format/locale.py
adactivexlsx2html/format/number.py
adactivexlsx2html/utils/__init__.py
adactivexlsx2html/utils/cell.py
adactivexlsx2html/utils/image.py
adactivexlsx2html-0.0.31.dist-info/LICENSE
adactivexlsx2html-0.0.31.dist-info/METADATA
adactivexlsx2html-0.0.31.dist-info/WHEEL
adactivexlsx2html-0.0.31.dist-info/top_level.txt
adactivexlsx2html-0.0.31.dist-info/RECORD
