Metadata-Version: 2.1
Name: adactivexlsx2html
Version: 0.0.31
Summary: A generic api for oauth2
Home-page: https://github.com/adactiveasia/adactivexlsx2html
Author: dev_adactive
Author-email: dev@adactive.asia
License: MIT
Keywords: converter xlsx html
Platform: UNKNOWN
Classifier: Development Status :: 3 - Alpha
Classifier: Intended Audience :: Developers
Classifier: License :: OSI Approved :: MIT License
Classifier: Programming Language :: Python
Classifier: Programming Language :: Python :: 3
Classifier: Programming Language :: Python :: 3.6
Classifier: Programming Language :: Python :: 3.7
Classifier: Programming Language :: Python :: 3.8
Classifier: Programming Language :: Python :: 3.9
Classifier: Programming Language :: Python :: 3.10
Classifier: Programming Language :: Python :: Implementation :: PyPy
Classifier: Topic :: Text Processing
Classifier: Topic :: Text Processing :: Markup :: HTML
Requires-Python: >=3.6, <4
License-File: LICENSE
Requires-Dist: six
Requires-Dist: openpyxl (>=2.4.8)
Requires-Dist: babel (>=2.3.4)
Requires-Dist: packaging (>=20.4)
